scatsol/__init__.py
scatsol/constant.py
scatsol/cylinder.py
scatsol/material.py
scatsol/sphere.py
scatsol/utils.py
scatsol-0.0.3.dist-info/METADATA
scatsol-0.0.3.dist-info/WHEEL
scatsol-0.0.3.dist-info/RECORD
